manishpy/__init__.py
manishpy/pattern.py
manishpy-1.1.2.dist-info/LICENCE
manishpy-1.1.2.dist-info/METADATA
manishpy-1.1.2.dist-info/WHEEL
manishpy-1.1.2.dist-info/top_level.txt
manishpy-1.1.2.dist-info/RECORD
